pytelecomm/__about__.py
pytelecomm/__init__.py
pytelecomm/__main__.py
pytelecomm-1.1.17.data/data/share/notebooks/pytelecomm.ipynb
pytelecomm-1.1.17.dist-info/METADATA
pytelecomm-1.1.17.dist-info/WHEEL
pytelecomm-1.1.17.dist-info/entry_points.txt
pytelecomm-1.1.17.dist-info/licenses/LICENSE
pytelecomm-1.1.17.dist-info/RECORD
