Metadata-Version: 2.4
Name: pytelecomm
Version: 1.1.17
Summary: Exploration of telecommunication theory in Python.
Project-URL: Documentation, https://github.com/capn-freako/pytelecomm#readme
Project-URL: Issues, https://github.com/capn-freako/pytelecomm/issues
Project-URL: Source, https://github.com/capn-freako/pytelecomm
Author-email: David Banas <capn.freako@gmail.com>
License-Expression: BSD-3-Clause
License-File: LICENSE
Classifier: Development Status :: 4 - Beta
Classifier: Programming Language :: Python
Classifier: Programming Language :: Python :: 3.8
Classifier: Programming Language :: Python :: 3.9
Classifier: Programming Language :: Python :: 3.10
Classifier: Programming Language :: Python :: 3.11
Classifier: Programming Language :: Python :: 3.12
Classifier: Programming Language :: Python :: Implementation :: CPython
Classifier: Programming Language :: Python :: Implementation :: PyPy
Requires-Python: >=3.8
Requires-Dist: jupyter
Requires-Dist: scipy
